awslambdahelper/__init__.py
awslambdahelper/cli.py
awslambdahelper/evaluation.py
awslambdahelper-1.1.14.data/scripts/lambdahelper-bundler
awslambdahelper-1.1.14.dist-info/DESCRIPTION.rst
awslambdahelper-1.1.14.dist-info/METADATA
awslambdahelper-1.1.14.dist-info/RECORD
awslambdahelper-1.1.14.dist-info/WHEEL
awslambdahelper-1.1.14.dist-info/metadata.json
awslambdahelper-1.1.14.dist-info/namespace_packages.txt
awslambdahelper-1.1.14.dist-info/top_level.txt
awslambdahelper-1.1.14.dist-info/zip-safe
